DirMan-0.1.7.dist-info/METADATA
DirMan-0.1.7.dist-info/WHEEL
dirman/__init__.py
dirman/dirman.cp312-win_amd64.pyd
DirMan-0.1.7.dist-info/RECORD
